shampoo/__init__.py
shampoo/shampoo.py
shampoo/schemas/push_message.json
shampoo/schemas/request.json
shampoo/schemas/response.json
shampoo-0.1.0b14.dist-info/LICENCE
shampoo-0.1.0b14.dist-info/METADATA
shampoo-0.1.0b14.dist-info/WHEEL
shampoo-0.1.0b14.dist-info/top_level.txt
shampoo-0.1.0b14.dist-info/RECORD
